spops_backend.cpython-310-x86_64-linux-gnu.so
spops_backend_cpu.cpython-310-x86_64-linux-gnu.so
spops/__init__.py
spops/csr_add.py
spops/csr_transpose.py
spops/sddmm.py
spops/spmm.py
spops_sm_75-0.0.0.dist-info/LICENSE
spops_sm_75-0.0.0.dist-info/METADATA
spops_sm_75-0.0.0.dist-info/WHEEL
spops_sm_75-0.0.0.dist-info/top_level.txt
spops_sm_75-0.0.0.dist-info/RECORD
